README.md
setup.py
tkintertable/App.py
tkintertable/Custom.py
tkintertable/Dialogs.py
tkintertable/Filtering.py
tkintertable/Plot.py
tkintertable/Prefs.py
tkintertable/TableFormula.py
tkintertable/TableModels.py
tkintertable/Table_images.py
tkintertable/Tables.py
tkintertable/Tables_IO.py
tkintertable/Testing.py
tkintertable/__init__.py
tkintertable.egg-info/PKG-INFO
tkintertable.egg-info/SOURCES.txt
tkintertable.egg-info/dependency_links.txt
tkintertable.egg-info/entry_points.txt
tkintertable.egg-info/requires.txt
tkintertable.egg-info/top_level.txt
tkintertable/../description.txt