Metadata-Version: 1.1
Name: tkintertable
Version: 1.3.1
Summary: Extendable table class for Tkinter
Home-page: https://github.com/dmnfarrell/tkintertable
Author: Damien Farrell
Author-email: farrell.damien@gmail.com
License: GPL v3
Keywords: tkinter,spreadsheet,table
Platform: UNKNOWN
Classifier: Operating System :: OS Independent
Classifier: Programming Language :: Python :: 2.7
Classifier: Programming Language :: Python :: 3
Classifier: Topic :: Software Development :: User Interfaces
Classifier: License :: OSI Approved :: GNU General Public License v3 (GPLv3)
Classifier: Development Status :: 4 - Beta
Classifier: Intended Audience :: Developers
Classifier: Intended Audience :: Science/Research
